Metadata-Version: 2.1
Name: fastencode
Version: 1.1
Summary: An easy way to use different encoding: bytes, hex, ascii array, binary, long
Home-page: https://github.com/user/reponame
Author: ES3
Author-email: ourteamscare@gmail.com
License: MIT
Download-URL: https://github.com/elyassaf/Easy-Encoding/archive/refs/tags/v_1.0.tar.gz
Keywords: encoding,hex,bytes,binary representation,decoding,ascii
Platform: UNKNOWN
Classifier: Development Status :: 5 - Production/Stable
Classifier: Intended Audience :: Developers
Classifier: Topic :: Software Development :: Build Tools
Classifier: License :: OSI Approved :: MIT License
Classifier: Programming Language :: Python :: 3
Classifier: Programming Language :: Python :: 3.4
Classifier: Programming Language :: Python :: 3.5
Classifier: Programming Language :: Python :: 3.6
Classifier: Programming Language :: Python :: 3.7
Classifier: Programming Language :: Python :: 3.8
Classifier: Programming Language :: Python :: 3.9
Classifier: Programming Language :: Python :: 3.10
Classifier: Programming Language :: Python :: 3.11
License-File: LICENSE.txt
